pyprocmail
