Metadata-Version: 1.1
Name: pyprocmail
Version: 0.1.1
Summary: Pyprocmail is a python parser and AST definitions for procmail's procmailrc files.
Home-page: https://github.com/nitmir/pyprocmail
Author: Valentin Samir
Author-email: valentin.samir@crans.org
License: GPLv3
Download-URL: https://github.com/nitmir/pyprocmail/releases
Keywords: procmail,parser,procmailrc,AST,tree,syntax
Platform: UNKNOWN
Classifier: Intended Audience :: Developers
Classifier: License :: OSI Approved :: GNU General Public License v3 (GPLv3)
Classifier: Programming Language :: Python
Classifier: Programming Language :: Python :: 2
Classifier: Topic :: Communications :: Email :: Filters
